lightregistry/__init__.py
lightregistry/client.py
lightregistry/consul.py
lightregistry/http.py
lightregistry/kvstore.py
lightregistry/registry.py
lightregistry/telemetry.py
literegistry/__init__.py
literegistry/api.py
literegistry/bandit.py
literegistry/cli.py
literegistry/client.py
literegistry/consul.py
literegistry/executable_wrapper.py
literegistry/gateway.py
literegistry/gateway_basic.py
literegistry/http.py
literegistry/kvstore.py
literegistry/redis.py
literegistry/registry.py
literegistry/sglang_wrapper.py
literegistry/shared_session.py
literegistry/telemetry.py
literegistry/vllm_wrapper.py
literegistry-1.0.2.dist-info/licenses/LICENSE
literegistry-1.0.2.dist-info/METADATA
literegistry-1.0.2.dist-info/WHEEL
literegistry-1.0.2.dist-info/entry_points.txt
literegistry-1.0.2.dist-info/top_level.txt
literegistry-1.0.2.dist-info/RECORD
