Metadata-Version: 2.4
Name: literegistry
Version: 1.0.2
Summary: Package for implementing service discovery in a really lite way.
Home-page: https://github.com/goncalorafaria/lightregistry
Author: Goncalo Faria
Author-email: gfaria@cs.washington.edu
Classifier: Programming Language :: Python :: 3
Classifier: License :: OSI Approved :: MIT License
Classifier: Operating System :: OS Independent
Requires-Python: >=3.6.0
License-File: LICENSE
Requires-Dist: aiohttp
Requires-Dist: asyncio
Requires-Dist: redis>=4.5.0
Dynamic: author
Dynamic: author-email
Dynamic: classifier
Dynamic: description
Dynamic: description-content-type
Dynamic: home-page
Dynamic: license-file
Dynamic: requires-dist
Dynamic: requires-python
Dynamic: summary
